metronomo_leo/1.wav
metronomo_leo/2.wav
metronomo_leo/__init__.py
metronomo_leo/metronomo.py
metronomo_leo/tempo_de_estudo_finalizado.wav
metronomo_leo-0.1.3.dist-info/METADATA
metronomo_leo-0.1.3.dist-info/WHEEL
metronomo_leo-0.1.3.dist-info/RECORD
